{
  "set_id": "SET_NONCOMPLIANT_42002",
  "category": "noncompliant",
  "seed": 42002,
  "difficulty": "high",
  "values": [
    {
      "attribute": "certificate_type",
      "value": 0.0,
      "unit": "categorical",
      "display_text": "B"
    },
    {
      "attribute": "ownership_declaration",
      "value": 0.0,
      "unit": "categorical",
      "display_text": "sole_owner"
    },
    {
      "attribute": "form_address",
      "value": 0.0,
      "unit": "string_pair",
      "display_text": "78 High Street, Moseley, B13 8HG"
    },
    {
      "attribute": "drawing_address",
      "value": 0.0,
      "unit": "string_pair",
      "display_text": "78 High St, Moseley, B13 8HG"
    },
    {
      "attribute": "stated_site_area",
      "value": 750.0,
      "unit": "m²",
      "display_text": "750.0m²"
    },
    {
      "attribute": "reference_parcel_area",
      "value": 720.0,
      "unit": "m²",
      "display_text": "720.0m²"
    },
    {
      "attribute": "reference_parcel_area",
      "value": 0.0,
      "unit": "m²",
      "display_text": "0.0m²"
    },
    {
      "attribute": "proposed_building_height",
      "value": 5.0,
      "unit": "metres",
      "display_text": "5.0m"
    },
    {
      "attribute": "approved_building_height",
      "value": 5.0,
      "unit": "metres",
      "display_text": "5.0m"
    },
    {
      "attribute": "proposed_building_footprint_area",
      "value": 80.0,
      "unit": "metres",
      "display_text": "80.0m"
    },
    {
      "attribute": "approved_building_footprint_area",
      "value": 80.0,
      "unit": "metres",
      "display_text": "80.0m"
    },
    {
      "attribute": "proposed_storeys",
      "value": 1.0,
      "unit": "metres",
      "display_text": "1.0m"
    },
    {
      "attribute": "approved_storeys",
      "value": 1.0,
      "unit": "metres",
      "display_text": "1.0m"
    },
    {
      "attribute": "building_height",
      "value": 5.34,
      "unit": "metres",
      "display_text": "5.3m"
    },
    {
      "attribute": "rear_garden_depth",
      "value": 17.29,
      "unit": "metres",
      "display_text": "17.3m"
    },
    {
      "attribute": "site_coverage",
      "value": 74.13,
      "unit": "percent",
      "display_text": "74.1%"
    },
    {
      "attribute": "building_footprint_area",
      "value": 141.58,
      "unit": "m²",
      "display_text": "141.6m²"
    },
    {
      "attribute": "total_site_area",
      "value": 740.51,
      "unit": "m²",
      "display_text": "740.5m²"
    },
    {
      "attribute": "zone_category",
      "value": 0.0,
      "unit": "categorical",
      "display_text": "residential"
    }
  ],
  "rule_verdicts": [
    {
      "rule_id": "C001",
      "outcome": "PASS",
      "evaluated_value": 0.0,
      "threshold": 0.0
    },
    {
      "rule_id": "C002",
      "outcome": "PASS",
      "evaluated_value": 0.0,
      "threshold": 0.0
    },
    {
      "rule_id": "C003",
      "outcome": "PASS",
      "evaluated_value": 750.0,
      "threshold": 1000.0
    },
    {
      "rule_id": "C004",
      "outcome": "PASS",
      "evaluated_value": 5.0,
      "threshold": 15.0
    },
    {
      "rule_id": "R001",
      "outcome": "PASS",
      "evaluated_value": 5.34,
      "threshold": 8.0
    },
    {
      "rule_id": "R002",
      "outcome": "PASS",
      "evaluated_value": 17.29,
      "threshold": 30.0
    },
    {
      "rule_id": "R003",
      "outcome": "FAIL",
      "evaluated_value": 74.13,
      "threshold": 50.0
    }
  ],
  "documents": [
    {
      "filename": "SET_NONCOMPLIANT_42002_form.pdf",
      "doc_type": "FORM",
      "file_format": "pdf",
      "extractions": [
        {
          "attribute": "site_address",
          "value": "64 Hawthorn Way, Leeds, OX1 3BQ",
          "text_rendered": "64 Hawthorn Way, Leeds, OX1 3BQ",
          "page": 1,
          "bounding_box": {
            "x": 794.55,
            "y": 677.89,
            "width": 1449.54,
            "height": 66.67,
            "page": 1
          },
          "entity_type": "ADDRESS"
        },
        {
          "attribute": "building_height",
          "value": 5.34,
          "text_rendered": "5.3m",
          "page": 3,
          "bounding_box": {
            "x": 1086.22,
            "y": 719.55,
            "width": 1157.87,
            "height": 66.67,
            "page": 3
          },
          "entity_type": "MEASUREMENT"
        },
        {
          "attribute": "site_coverage",
          "value": 74.13,
          "text_rendered": "74.1%",
          "page": 3,
          "bounding_box": {
            "x": 1086.22,
            "y": 969.55,
            "width": 1157.87,
            "height": 66.67,
            "page": 3
          },
          "entity_type": "MEASUREMENT"
        }
      ],
      "degraded_extractions": [
        {
          "attribute": "site_address",
          "value": "64 Hawthorn Way, Leeds, OX1 3BQ",
          "text_rendered": "64 Hawthorn Way, Leeds, OX1 3BQ",
          "page": 1,
          "bounding_box": {
            "x": 794.55,
            "y": 677.89,
            "width": 1449.54,
            "height": 66.67,
            "page": 1
          },
          "entity_type": "ADDRESS"
        },
        {
          "attribute": "building_height",
          "value": 5.34,
          "text_rendered": "5.3m",
          "page": 3,
          "bounding_box": {
            "x": 1086.22,
            "y": 719.55,
            "width": 1157.87,
            "height": 66.67,
            "page": 3
          },
          "entity_type": "MEASUREMENT"
        },
        {
          "attribute": "site_coverage",
          "value": 74.13,
          "text_rendered": "74.1%",
          "page": 3,
          "bounding_box": {
            "x": 1086.22,
            "y": 969.55,
            "width": 1157.87,
            "height": 66.67,
            "page": 3
          },
          "entity_type": "MEASUREMENT"
        }
      ]
    },
    {
      "filename": "SET_NONCOMPLIANT_42002_site_plan.pdf",
      "doc_type": "DRAWING",
      "file_format": "pdf",
      "extractions": [],
      "degraded_extractions": []
    },
    {
      "filename": "SET_NONCOMPLIANT_42002_floor_plan.pdf",
      "doc_type": "DRAWING",
      "file_format": "pdf",
      "extractions": [],
      "degraded_extractions": []
    },
    {
      "filename": "SET_NONCOMPLIANT_42002_elevation.png",
      "doc_type": "DRAWING",
      "file_format": "png",
      "extractions": [
        {
          "attribute": "building_height",
          "value": 5.34,
          "text_rendered": "5.3m",
          "page": 1,
          "bounding_box": {
            "x": 2062.0,
            "y": 2803.0,
            "width": 115.0,
            "height": 37.0,
            "page": 1
          },
          "entity_type": "MEASUREMENT"
        }
      ],
      "degraded_extractions": [
        {
          "attribute": "building_height",
          "value": 5.34,
          "text_rendered": "5.3m",
          "page": 1,
          "bounding_box": {
            "x": 2062.0,
            "y": 2803.0,
            "width": 115.0,
            "height": 37.0,
            "page": 1
          },
          "entity_type": "MEASUREMENT"
        }
      ]
    },
    {
      "filename": "SET_NONCOMPLIANT_42002_elevation.png",
      "doc_type": "DRAWING",
      "file_format": "png",
      "extractions": [
        {
          "attribute": "building_height",
          "value": 5.34,
          "text_rendered": "5.3m",
          "page": 1,
          "bounding_box": {
            "x": 1970.0,
            "y": 2826.0,
            "width": 115.0,
            "height": 37.0,
            "page": 1
          },
          "entity_type": "MEASUREMENT"
        }
      ],
      "degraded_extractions": [
        {
          "attribute": "building_height",
          "value": 5.34,
          "text_rendered": "5.3m",
          "page": 1,
          "bounding_box": {
            "x": 1970.0,
            "y": 2826.0,
            "width": 115.0,
            "height": 37.0,
            "page": 1
          },
          "entity_type": "MEASUREMENT"
        }
      ]
    },
    {
      "filename": "SET_NONCOMPLIANT_42002_floor_plan.pdf",
      "doc_type": "DRAWING",
      "file_format": "pdf",
      "extractions": [],
      "degraded_extractions": []
    }
  ],
  "degradation": {
    "preset": "heavy_scan",
    "seed": 42002
  },
  "edge_case_strategy": null
}